coder_screensaver/__init__.py
coder_screensaver-0.1.3.dist-info/licenses/LICENSE
coder_screensaver-0.1.3.dist-info/METADATA
coder_screensaver-0.1.3.dist-info/WHEEL
coder_screensaver-0.1.3.dist-info/entry_points.txt
coder_screensaver-0.1.3.dist-info/top_level.txt
coder_screensaver-0.1.3.dist-info/RECORD
