Metadata-Version: 2.4
Name: coder-screensaver
Version: 0.1.3
Summary: Animated code screensaver with syntax highlighting - displays source code as if being typed in real-time
Author-email: Sinan Islekdemir <sinan@islekdemir.com>
License: MIT
Project-URL: Homepage, https://github.com/sinanislekdemir/coder-screensaver
Project-URL: Repository, https://github.com/sinanislekdemir/coder-screensaver
Project-URL: Issues, https://github.com/sinanislekdemir/coder-screensaver/issues
Keywords: screensaver,code,syntax-highlighting,terminal,animation,typing
Classifier: Development Status :: 4 - Beta
Classifier: Environment :: Console :: Curses
Classifier: Intended Audience :: Developers
Classifier: License :: OSI Approved :: MIT License
Classifier: Operating System :: POSIX :: Linux
Classifier: Operating System :: MacOS
Classifier: Programming Language :: Python :: 3
Classifier: Programming Language :: Python :: 3.8
Classifier: Programming Language :: Python :: 3.9
Classifier: Programming Language :: Python :: 3.10
Classifier: Programming Language :: Python :: 3.11
Classifier: Programming Language :: Python :: 3.12
Classifier: Topic :: Software Development
Classifier: Topic :: Terminals
Classifier: Topic :: Text Editors
Requires-Python: >=3.8
License-File: LICENSE
Requires-Dist: pygments>=2.0.0
Provides-Extra: dev
Requires-Dist: pytest>=7.0; extra == "dev"
Requires-Dist: black>=23.0; extra == "dev"
Requires-Dist: ruff>=0.1.0; extra == "dev"
Dynamic: license-file
